README.md
setup.cfg
setup.py
anygraph/__init__.py
anygraph/linkers.py
anygraph/tools.py
anygraph/visitors.py
anygraph/wrapper.py
anygraph.egg-info/PKG-INFO
anygraph.egg-info/SOURCES.txt
anygraph.egg-info/dependency_links.txt
anygraph.egg-info/top_level.txt