Metadata-Version: 1.2
Name: anygraph
Version: 0.2.1
Summary: add any graph structure between classes with 2 simple classes
Home-page: https://github.com/gemerden/anygraph
Author: Lars van Gemerden
Author-email: gemerden@gmail.com
License: MIT License
Keywords: graphs trees descriptors iterators easy-to-use depth-first breadth-first dijkstra astar A*
Platform: UNKNOWN
Classifier: Development Status :: 4 - Beta
Classifier: Intended Audience :: Developers
Classifier: Topic :: Software Development
Classifier: License :: OSI Approved :: MIT License
Classifier: Programming Language :: Python :: 3.6
Classifier: Programming Language :: Python :: 3.7
Classifier: Programming Language :: Python :: 3.8
Requires-Python: >=3.6
